clony/__init__.py
clony/_version.py
clony/cli.py
clony/core/__init__.py
clony/core/diff.py
clony/core/objects.py
clony/core/refs.py
clony/core/repository.py
clony/internals/__init__.py
clony/internals/checkout.py
clony/internals/commit.py
clony/internals/log.py
clony/internals/merge.py
clony/internals/reset.py
clony/internals/staging.py
clony/internals/status.py
clony/utils/__init__.py
clony/utils/logger.py
clony-0.1.12.dist-info/METADATA
clony-0.1.12.dist-info/WHEEL
clony-0.1.12.dist-info/entry_points.txt
clony-0.1.12.dist-info/top_level.txt
clony-0.1.12.dist-info/RECORD
