Metadata-Version: 2.1
Name: clony
Version: 0.1.12
Summary: 🛠️ A modern Git clone tool with a colorful CLI interface. ✨ Clony provides intuitive Git commands with clear output, smart file staging, and flexible repository management.
Author-email: Rohit Vilas Ingole <rohit.vilas.ingole@gmail.com>
License: # The MIT License
Project-URL: Homepage, https://github.com/rohitvilas/clony
Classifier: Programming Language :: Python :: 3
Classifier: License :: OSI Approved :: MIT License
Classifier: Operating System :: OS Independent
Requires-Python: >=3.10
Requires-Dist: rich>=13.0.0
Requires-Dist: click>=8.0.0
Requires-Dist: colorlog>=6.8.0
Requires-Dist: colorama>=0.4.6
Provides-Extra: dev
Requires-Dist: pytest>=7.0.0; extra == "dev"
Requires-Dist: pytest-cov>=4.0.0; extra == "dev"
Requires-Dist: ruff>=0.0.270; extra == "dev"
